minidocker/__init__.py
minidocker/__main__.py
minidocker/_find_image.py
minidocker/_util.py
minidocker/py/__init__.py
minidocker/py/__main__.py
minidocker/py/_build.py
minidocker/py/_build_for_pkg.py
minidocker/py/_build_for_proj.py
minidocker/py/_run.py
minidocker/py/_util.py
minidocker/py/githooks/README
minidocker/py/githooks/pre-commit
minidocker-0.1.7.dist-info/licenses/LICENSE
minidocker-0.1.7.dist-info/WHEEL
minidocker-0.1.7.dist-info/METADATA
minidocker-0.1.7.dist-info/RECORD
