Metadata-Version: 2.4
Name: minidocker
Version: 0.1.7
Summary: minidocker
Author-email: Zepu Zhang <zepu.zhang@gmail.com>
Requires-Python: >=3.8
Classifier: Intended Audience :: Developers
Classifier: Programming Language :: Python :: 3
Classifier: Topic :: Software Development :: Libraries :: Python Modules
License-File: LICENSE
Requires-Dist: ruff
Requires-Dist: toml; python_version < '3.11'
Requires-Dist: pytest ; extra == "test"
Project-URL: Source, https://github.com/zpz/minidocker
Provides-Extra: test
